forkedthanks/__init__.py
forkedthanks/forkedthanks.py
forkedthanks/text.py
forkedthanks-0.1.0.dist-info/DESCRIPTION.rst
forkedthanks-0.1.0.dist-info/METADATA
forkedthanks-0.1.0.dist-info/RECORD
forkedthanks-0.1.0.dist-info/WHEEL
forkedthanks-0.1.0.dist-info/entry_points.txt
forkedthanks-0.1.0.dist-info/metadata.json
forkedthanks-0.1.0.dist-info/top_level.txt
